{
  "doc_id": "2020-09-14-CAWRIT-310-2017",
  "num": "CAWRIT 310/2017",
  "date_str": "2020-09-14",
  "description": "Lanka Electricity Company (Private) Limited, Vs. T. Piyasoma, & Others before  Hon. Arjuna Obeyesekere, J",
  "url_pdf": "https://courtofappeal.lk/?melsta_doc_download=1&doc_id=6918d7b5-e923-4c5c-9016-a1967afe14ed&filename=ca.310.17.final.pdf",
  "parties": "Lanka Electricity Company (Private) Limited, Vs. T. Piyasoma, & Others",
  "judgement_by": " Hon. Arjuna Obeyesekere, J",
  "keywords": "",
  "legistation": ""
}